linalg_basic/__init__.py
linalg_basic/linalg_basic.py
linalg_basic-0.1.0.dist-info/LICENSE
linalg_basic-0.1.0.dist-info/METADATA
linalg_basic-0.1.0.dist-info/WHEEL
linalg_basic-0.1.0.dist-info/top_level.txt
linalg_basic-0.1.0.dist-info/RECORD
