Metadata-Version: 2.1
Name: linalg-basic
Version: 0.1.0
Summary: A slight variation upon Joel Grus's linear algebra library from 'Data Science from Scratch' chapter 4, created to build my 'Deluxe' library on top
Author: Joel Grus
Author-email: Andrew Rose <andrew.rose43@gmail.com>
Project-URL: Homepage, https://github.com/andrewrose43/DataScienceFromScratch_CodeTheBook
Classifier: Programming Language :: Python :: 3
Classifier: License :: OSI Approved :: MIT License
Classifier: Operating System :: OS Independent
Requires-Python: >=3.10
License-File: LICENSE
